footap/__init__.py
footap/config.py
footap/main.py
footap/video_processing.py
footap-1.6.1.dist-info/LICENSE
footap-1.6.1.dist-info/METADATA
footap-1.6.1.dist-info/WHEEL
footap-1.6.1.dist-info/entry_points.txt
footap-1.6.1.dist-info/top_level.txt
footap-1.6.1.dist-info/RECORD
