Metadata-Version: 2.2
Name: footap
Version: 1.6.1
Summary: Package d'analyse des touches de balle au football
Author: Dims
Classifier: Development Status :: 4 - Beta
Classifier: Intended Audience :: Developers
Classifier: License :: OSI Approved :: MIT License
Classifier: Operating System :: OS Independent
Classifier: Programming Language :: Python :: 3.10
Classifier: Topic :: Software Development :: Libraries :: Python Modules
Classifier: Topic :: Multimedia :: Video :: Capture
Requires-Python: >=3.7
License-File: LICENSE
Requires-Dist: mediapipe==0.10.7
Requires-Dist: numpy==1.24.3
Requires-Dist: ultralytics==8.3.69
Requires-Dist: Pillow==10.1.0
Requires-Dist: opencv-contrib-python==4.11.0.86
Requires-Dist: opencv-contrib-python-headless==4.11.0.86
Requires-Dist: opencv-python==4.11.0.86
Requires-Dist: torch==2.1.1
Requires-Dist: torchvision==0.16.1
Dynamic: author
Dynamic: classifier
Dynamic: description
Dynamic: description-content-type
Dynamic: requires-dist
Dynamic: requires-python
Dynamic: summary
